mynyt/MyNYT.py
mynyt/__init__.py
mynyt-1.4.7.dist-info/METADATA
mynyt-1.4.7.dist-info/WHEEL
mynyt-1.4.7.dist-info/top_level.txt
mynyt-1.4.7.dist-info/RECORD
