Metadata-Version: 2.4
Name: mynyt
Version: 1.4.7
Summary: a package that brings the New York Times to you with rss feeds and emails
Author: Kevin Zhu
Author-email: kzhu2099@gmail.com
Maintainer: Kevin Zhu
Maintainer-email: kzhu2099@gmail.com
License: MIT License
Project-URL: Homepage, https://github.com/kzhu2099/My-NYT
Project-URL: Issues, https://github.com/kzhu2099/My-NYT/issues
Classifier: Development Status :: 5 - Production/Stable
Classifier: Intended Audience :: Developers
Classifier: Intended Audience :: End Users/Desktop
Classifier: License :: OSI Approved :: MIT License
Classifier: Natural Language :: English
Classifier: Operating System :: OS Independent
Classifier: Programming Language :: Python :: 3
Classifier: Topic :: Communications :: Email
Classifier: Topic :: Internet :: WWW/HTTP :: Dynamic Content :: News/Diary
Requires-Python: >=3.9
Requires-Dist: feedparser
Requires-Dist: requests
Requires-Dist: pytz
Requires-Dist: kzutil
